newbee/__init__.py
newbee-0.0.1b0.dist-info/METADATA
newbee-0.0.1b0.dist-info/WHEEL
newbee-0.0.1b0.dist-info/licenses/LICENSE
newbee-0.0.1b0.dist-info/RECORD
