Metadata-Version: 2.1
Name: newbee
Version: 0.0.1b0
Summary: newbee
Project-URL: Source, https://github.com/wh1isper/newbee
Author-email: wh1isper <9573586@qq.com>
License: BSD license
License-File: LICENSE
Keywords: newbee
Classifier: Programming Language :: Python :: 3
Classifier: Programming Language :: Python :: 3.8
Classifier: Programming Language :: Python :: 3.9
Classifier: Programming Language :: Python :: 3.10
Classifier: Programming Language :: Python :: 3.11
Requires-Python: >=3.8
Provides-Extra: test
Requires-Dist: pytest; extra == 'test'
